{
	"id": "62b045fc98497201a5001247",
	"title": "Polus_inControl_canDelete",
	"hookType": "canDelete",
	"function": "function canDelete(props) {\n   const { item, user } = props;\n   let flag_p = false;\n   const user_ID = user.id;\n   console.log(item);\n   if (item.data.responsible.user) {\n         if (user_ID.includes(item.data.responsible.user)) {\n            flag_p = true;\n         }\n    }\n  \n   return flag_p;\n}",
	"form": "62a1f67e98497201a5000f1c",
	"relationsData": [],
	"createdDate": 1655719420126,
	"updatedDate": 1655719514830,
	"owner": null,
	"assignedTo": null,
	"parent": null
}